fkat/__init__.py
fkat/predict.py
fkat/py.typed
fkat/test.py
fkat/train.py
fkat/validate.py
fkat/data/__init__.py
fkat/data/data_module.py
fkat/data/dict.py
fkat/data/sharded.py
fkat/data/shm.py
fkat/data/datasets/__init__.py
fkat/data/datasets/dict.py
fkat/data/datasets/json.py
fkat/data/datasets/map.py
fkat/data/datasets/parquet.py
fkat/data/datasets/sized.py
fkat/data/samplers/__init__.py
fkat/data/samplers/dict.py
fkat/data/samplers/sized.py
fkat/data/samplers/strategies.py
fkat/pytorch/__init__.py
fkat/pytorch/loggers.py
fkat/pytorch/utilities.py
fkat/pytorch/actions/__init__.py
fkat/pytorch/actions/aws/__init__.py
fkat/pytorch/actions/aws/batch.py
fkat/pytorch/actions/aws/ec2.py
fkat/pytorch/callbacks/__init__.py
fkat/pytorch/callbacks/gc.py
fkat/pytorch/callbacks/loggers.py
fkat/pytorch/callbacks/cuda/__init__.py
fkat/pytorch/callbacks/cuda/cache.py
fkat/pytorch/callbacks/cuda/memory.py
fkat/pytorch/callbacks/cuda/nsys.py
fkat/pytorch/callbacks/cuda/nvtx.py
fkat/pytorch/callbacks/cuda/xid.py
fkat/pytorch/callbacks/debugging/__init__.py
fkat/pytorch/callbacks/debugging/introspection.py
fkat/pytorch/callbacks/debugging/optimizer.py
fkat/pytorch/callbacks/logging/__init__.py
fkat/pytorch/callbacks/logging/heartbeat.py
fkat/pytorch/callbacks/logging/throughput.py
fkat/pytorch/callbacks/logging/validation_metrics.py
fkat/pytorch/callbacks/monitoring/__init__.py
fkat/pytorch/callbacks/monitoring/crash.py
fkat/pytorch/callbacks/monitoring/dp.py
fkat/pytorch/callbacks/monitoring/hardware_stats.py
fkat/pytorch/callbacks/monitoring/shutdown.py
fkat/pytorch/callbacks/profiling/__init__.py
fkat/pytorch/callbacks/profiling/flops.py
fkat/pytorch/callbacks/profiling/memray.py
fkat/pytorch/callbacks/profiling/torch.py
fkat/pytorch/callbacks/profiling/viztracer.py
fkat/pytorch/schedule/__init__.py
fkat/pytorch/schedule/base.py
fkat/pytorch/schedule/mlflow.py
fkat/utils/__init__.py
fkat/utils/boto3.py
fkat/utils/config.py
fkat/utils/logging.py
fkat/utils/mlflow.py
amzn_fkat-0.1.1.dist-info/METADATA
amzn_fkat-0.1.1.dist-info/WHEEL
amzn_fkat-0.1.1.dist-info/licenses/LICENSE
amzn_fkat-0.1.1.dist-info/licenses/NOTICE
amzn_fkat-0.1.1.dist-info/RECORD
